{
  "configurations": [
    {
      "name": "Win32",
      "includePath": [
        "${workspaceFolder}/**",
        "${workspaceFolder}/src/**",
        "${workspaceFolder}/src/util/**",
        "${workspaceFolder}/src/hapi/**",
        "C:/Program Files/Side Effects Software/Houdini 21.0.631/toolkit/include",
        "/opt/hfs21.0/toolkit/include"
      ],
      "defines": ["_DEBUG", "UNICODE", "_UNICODE"],
      "windowsSdkVersion": "10.0.22000.0",
      "compilerPath": "C:/Program Files/Microsoft Visual Studio/2022/Community/VC/Tools/MSVC/14.38.33130/bin/Hostx64/x86/cl.exe",
      "cStandard": "c17",
      "cppStandard": "c++17",
      "intelliSenseMode": "windows-msvc-x64"
    },
    {
      "name": "Linux",
      "includePath": [
        "${workspaceFolder}/**",
        // Godot-cpp submodule paths
        "${workspaceFolder}/godot-cpp/include",
        "${workspaceFolder}/godot-cpp/gen/include",
        "${workspaceFolder}/godot-cpp/gdextension",
        "${workspaceFolder}/src/**",
        "${workspaceFolder}/src/util/**",
        "${workspaceFolder}/src/hapi/**",
        // Houdini on Linux
        "/opt/hfs21.0/toolkit/include"
      ],
      "defines": [
        "GDEXTENSION",      
        "DEBUG_ENABLED",
        "LINUX",            
        "_DEBUG"            
      ],
      "compilerPath": "/usr/bin/g++",
      "cStandard": "c17",
      "cppStandard": "c++17",
      "intelliSenseMode": "linux-gcc-x64"
    }
  ],
  "version": 4
}
